fast_rl/__init__.py
fast_rl/agents/__init__.py
fast_rl/agents/ddpg.py
fast_rl/agents/ddpg_models.py
fast_rl/agents/dqn.py
fast_rl/agents/dqn_models.py
fast_rl/core/Interpreter.py
fast_rl/core/__init__.py
fast_rl/core/agent_core.py
fast_rl/core/basic_train.py
fast_rl/core/data_block.py
fast_rl/core/data_structures.py
fast_rl/core/layers.py
fast_rl/core/metrics.py
fast_rl/core/train.py
fast_rl/util/__init__.py
fast_rl/util/exceptions.py
fast_rl/util/misc.py
tests/__init__.py
tests/conftest.py
tests/test_agent_core.py
tests/test_basic_train.py
tests/test_data_block.py
tests/test_data_structures.py
tests/test_ddpg.py
tests/test_dqn.py
tests/test_metrics.py
tests/test_train.py
fast_rl-1.0.1.dist-info/LICENSE.txt
fast_rl-1.0.1.dist-info/METADATA
fast_rl-1.0.1.dist-info/WHEEL
fast_rl-1.0.1.dist-info/top_level.txt
fast_rl-1.0.1.dist-info/RECORD
