Metadata-Version: 2.1
Name: fast-rl
Version: 1.0.1
Summary: Fastai for computer vision and tabular learning has been amazing. One would wish that this would be the same for RL. The purpose of this repo is to have a framework that is as easy as possible to start, but also designed for testing new agents. 
Home-page: https://github.com/josiahls/fast-reinforcement-learning
Author: Josiah Laivins
Author-email: jlaivins@uncc.edu
License: UNKNOWN
Platform: UNKNOWN
Classifier: Development Status :: 3 - Alpha
Classifier: Programming Language :: Python :: 3
Classifier: License :: OSI Approved :: Apache Software License
Classifier: Operating System :: OS Independent
Requires-Python: >=3.6
Requires-Dist: fastai (>=1.0.59)
Requires-Dist: gym[atari,box2d]
Requires-Dist: jupyter
Provides-Extra: all
Requires-Dist: gym-minigrid ; extra == 'all'
Requires-Dist: moviepy ; extra == 'all'
